Metadata-Version: 2.1
Name: pyqode3-python
Version: 4.0.1
Summary: pyqode.python is an extension of pyqode.core that brings support
Keywords: CodeEdit,PyQt,editor,widget,qt,Python
Author-email: Colin Duquesnoy <colin.duquesnoy@gmail.com>, Sebastiaan Mathôt <s.mathot@cogsci.nl>
Requires-Python: >=3.7
Requires-Dist: qtawesome
Requires-Dist: pyflakes
Requires-Dist: autopep8
Requires-Dist: pep8
Requires-Dist: jedi
Requires-Dist: docutils
Project-URL: Documentation, https://github.com/open-cogsci/pyqode.python
Project-URL: Source, https://github.com/open-cogsci/pyqode.python
